adaptive_core_ext.cpython-313-x86_64-linux-gnu.so
include/adaptive.h
include/adaptive_core/cluster.hpp
include/adaptive_core/cluster_backend.hpp
include/adaptive_core/profile.hpp
include/adaptive_core/result.hpp
include/adaptive_core/router.hpp
include/adaptive_core/scorer.hpp
include/adaptive_core/cuda/cluster_cuda.hpp
lib/libadaptive_c.so
lib/libadaptive_c.so.0
lib/libadaptive_c.so.0.1.11
lib/libadaptive_core.a
adaptive_router_core_cu12-0.1.11.dist-info/METADATA
adaptive_router_core_cu12-0.1.11.dist-info/WHEEL
adaptive_router_core_cu12-0.1.11.dist-info/RECORD
