Metadata-Version: 2.1
Name: adaptive-router-core-cu12
Version: 0.1.11
Summary: C++ inference core for Adaptive Router (CUDA 12.x)
